dataplicity/__init__.py
dataplicity/__main__.py
dataplicity/_version.py
dataplicity/app.py
dataplicity/client.py
dataplicity/clockcheck.py
dataplicity/compat.py
dataplicity/constants.py
dataplicity/device_meta.py
dataplicity/directory_scanner.py
dataplicity/disk_tools.py
dataplicity/iptool.py
dataplicity/jsonrpc.py
dataplicity/limiter.py
dataplicity/m2mmanager.py
dataplicity/portforward.py
dataplicity/remote_directory.py
dataplicity/rpi.py
dataplicity/scan_directory.py
dataplicity/subcommand.py
dataplicity/tags.py
dataplicity/m2m/__init__.py
dataplicity/m2m/bencode.py
dataplicity/m2m/commandservice.py
dataplicity/m2m/dispatcher.py
dataplicity/m2m/echoservice.py
dataplicity/m2m/fileservice.py
dataplicity/m2m/packetbase.py
dataplicity/m2m/packets.py
dataplicity/m2m/proxy.py
dataplicity/m2m/remoteprocess.py
dataplicity/m2m/wsclient.py
dataplicity/subcommands/__init__.py
dataplicity/subcommands/run.py
dataplicity/subcommands/version.py
dataplicity-0.5.13.dist-info/licenses/LICENSE.txt
dataplicity-0.5.13.dist-info/METADATA
dataplicity-0.5.13.dist-info/WHEEL
dataplicity-0.5.13.dist-info/entry_points.txt
dataplicity-0.5.13.dist-info/top_level.txt
dataplicity-0.5.13.dist-info/zip-safe
dataplicity-0.5.13.dist-info/RECORD
